flask_oidc/__init__.py
flask_oidc/model.py
flask_oidc/signals.py
flask_oidc/views.py
flask_oidc-2.3.0.dist-info/LICENSES/BSD-2-Clause.txt
flask_oidc-2.3.0.dist-info/METADATA
flask_oidc-2.3.0.dist-info/WHEEL
flask_oidc-2.3.0.dist-info/RECORD
