Metadata-Version: 2.3
Name: flask-oidc
Version: 2.3.0
Summary: OpenID Connect extension for Flask
License: BSD-2-Clause
Author: Erica Ehrhardt
Requires-Python: >=3.8,<4.0
Classifier: Environment :: Web Environment
Classifier: Framework :: Flask
Classifier: Intended Audience :: Developers
Classifier: License :: OSI Approved :: BSD License
Classifier: Operating System :: OS Independent
Classifier: Programming Language :: Python
Classifier: Programming Language :: Python :: 3
Classifier: Programming Language :: Python :: 3.8
Classifier: Programming Language :: Python :: 3.9
Classifier: Programming Language :: Python :: 3.10
Classifier: Programming Language :: Python :: 3.11
Classifier: Programming Language :: Python :: 3.12
Classifier: Programming Language :: Python :: 3.13
Classifier: Topic :: Internet :: WWW/HTTP :: Dynamic Content
Classifier: Topic :: Software Development :: Libraries :: Python Modules
Requires-Dist: authlib (>=1.2.0,<2.0.0)
Requires-Dist: blinker (>=1.4.0,<2.0.0)
Requires-Dist: flask (>=0.12.2,<4.0.0)
Requires-Dist: requests (>=2.20.0,<3.0.0)
Project-URL: Homepage, https://github.com/fedora-infra/flask-oidc
Project-URL: Repository, https://github.com/fedora-infra/flask-oidc
